{
  "collectionName": "components_sections_solutions_s",
  "info": {
    "displayName": "Solutions ",
    "icon": "air-freshener",
    "description": ""
  },
  "options": {},
  "attributes": {
    "heading": {
      "type": "component",
      "repeatable": false,
      "component": "elements.heading",
      "required": true
    },
    "solutionCards": {
      "type": "component",
      "repeatable": true,
      "component": "elements.solution-card",
      "required": true,
      "max": 3
    }
  }
}
